autoauthnumber/__init__.py
autoauthnumber/author_number.py
autoauthnumber/mk_Pron.py
autoauthnumber/Translate_API/BaiDu_API.py
autoauthnumber/Translate_API/YouDao_API.py
autoauthnumber/Translate_API/__init__.py
autoauthnumber-1.2.2.dist-info/LICENSE
autoauthnumber-1.2.2.dist-info/METADATA
autoauthnumber-1.2.2.dist-info/WHEEL
autoauthnumber-1.2.2.dist-info/top_level.txt
autoauthnumber-1.2.2.dist-info/zip-safe
autoauthnumber-1.2.2.dist-info/RECORD
