Metadata-Version: 2.1
Name: autoauthnumber
Version: 1.2.2
Summary: This is a library about automatic number-taking of 'General Chinese Author Number Table'. At present, there is only one way to take the number, that is, directly looking up the table.In the future, we will adapt to a variety of author numbering methods, please wait.
Home-page: https://github.com/thedayofthedoctor/aan
Author: Matt Belfast Brown
Author-email: thedayofthedo@gmail.com
License: GPL-3.0 LICENSE
Project-URL: Documentation, http://belfast.web3v.work/program/doc/aan/
Project-URL: Bug Tracker, https://github.com/thedayofthedoctor/aan/issues
Keywords: auto,author number
Platform: any
Classifier: Programming Language :: Python :: 3.7
Classifier: Programming Language :: Python :: 3.8
Classifier: Programming Language :: Python :: 3.9
Classifier: Programming Language :: Python :: 3.10
Classifier: Programming Language :: Python :: 3.11
Classifier: License :: OSI Approved :: GNU General Public License v3 (GPLv3)
Requires-Python: >=3.7,<=3.11
License-File: LICENSE
Requires-Dist: pypinyin
Requires-Dist: requests
